[{"uri":"/assets/pictures/1sonder/sonder_(6).jpg","thumb_uri":"/assets/thumbnails/1sonder/thumb_sonder_(6).jpg","title":"Sonder","alt":"Sonder by Syria Pace","_id":"sonder_(6).jpg","collection":"1sonder","decorativeCollectionName":"sonder","width":1628,"height":1080},{"uri":"/assets/pictures/1sonder/sonder_(8).jpg","thumb_uri":"/assets/thumbnails/1sonder/thumb_sonder_(8).jpg","title":"Sonder","alt":"Sonder by Syria Pace","_id":"sonder_(8).jpg","collection":"1sonder","decorativeCollectionName":"sonder","width":1259,"height":1920},{"uri":"/assets/pictures/1sonder/sonder_(7).jpg","thumb_uri":"/assets/thumbnails/1sonder/thumb_sonder_(7).jpg","title":"Sonder","alt":"Sonder by Syria Pace","_id":"sonder_(7).jpg","collection":"1sonder","decorativeCollectionName":"sonder","width":1260,"height":1920},{"uri":"/assets/pictures/2brighton-marina/BrightonMarina_(1).jpg","thumb_uri":"/assets/thumbnails/2brighton-marina/thumb_BrightonMarina_(1).jpg","title":"Brighton Marina","alt":"Brighton Marina by Syria Pace","_id":"BrightonMarina_(1).jpg","collection":"2brighton-marina","decorativeCollectionName":"brighton-marina","width":1539,"height":1025},{"uri":"/assets/pictures/2brighton-marina/BrightonMarina_(3).jpg","thumb_uri":"/assets/thumbnails/2brighton-marina/thumb_BrightonMarina_(3).jpg","title":"Brighton Marina","alt":"Brighton Marina by Syria Pace","_id":"BrightonMarina_(3).jpg","collection":"2brighton-marina","decorativeCollectionName":"brighton-marina","width":1600,"height":1066},{"uri":"/assets/pictures/2brighton-marina/BrightonMarina_(2).jpg","thumb_uri":"/assets/thumbnails/2brighton-marina/thumb_BrightonMarina_(2).jpg","title":"Brighton Marina","alt":"Brighton Marina by Syria Pace","_id":"BrightonMarina_(2).jpg","collection":"2brighton-marina","decorativeCollectionName":"brighton-marina","width":1045,"height":1568},{"uri":"/assets/pictures/2brighton-marina/BrightonMarina_(4).jpg","thumb_uri":"/assets/thumbnails/2brighton-marina/thumb_BrightonMarina_(4).jpg","title":"Brighton Marina","alt":"Brighton Marina by Syria Pace","_id":"BrightonMarina_(4).jpg","collection":"2brighton-marina","decorativeCollectionName":"brighton-marina","width":1600,"height":1066},{"uri":"/assets/pictures/2brighton-marina/BrightonMarina_(5).jpg","thumb_uri":"/assets/thumbnails/2brighton-marina/thumb_BrightonMarina_(5).jpg","title":"Brighton Marina","alt":"Brighton Marina by Syria Pace","_id":"BrightonMarina_(5).jpg","collection":"2brighton-marina","decorativeCollectionName":"brighton-marina","width":1600,"height":1066},{"uri":"/assets/pictures/1sonder/sonder_(1).jpg","thumb_uri":"/assets/thumbnails/1sonder/thumb_sonder_(1).jpg","title":"Sonder","alt":"Sonder by Syria Pace","_id":"sonder_(1).jpg","collection":"1sonder","decorativeCollectionName":"sonder","width":1920,"height":1268},{"uri":"/assets/pictures/1sonder/sonder_(4).jpg","thumb_uri":"/assets/thumbnails/1sonder/thumb_sonder_(4).jpg","title":"Sonder","alt":"Sonder by Syria Pace","_id":"sonder_(4).jpg","collection":"1sonder","decorativeCollectionName":"sonder","width":1920,"height":1263},{"uri":"/assets/pictures/1sonder/sonder_(5).jpg","thumb_uri":"/assets/thumbnails/1sonder/thumb_sonder_(5).jpg","title":"Sonder","alt":"Sonder by Syria Pace","_id":"sonder_(5).jpg","collection":"1sonder","decorativeCollectionName":"sonder","width":1920,"height":1260},{"uri":"/assets/pictures/3misc/Misc_Camera.jpg","thumb_uri":"/assets/thumbnails/3misc/thumb_Misc_Camera.jpg","title":"Comet Camera","alt":"Comet Camera by Syria Pace","_id":"Misc_Camera.jpg","collection":"3misc","decorativeCollectionName":"misc","width":1080,"height":1080},{"uri":"/assets/pictures/3misc/Misc_Pin.jpg","thumb_uri":"/assets/thumbnails/3misc/thumb_Misc_Pin.jpg","title":"Pin","alt":"Pin by Syria Pace","_id":"Misc_Pin.jpg","collection":"3misc","decorativeCollectionName":"misc","width":1080,"height":1080},{"uri":"/assets/pictures/1sonder/sonder_(3).jpg","thumb_uri":"/assets/thumbnails/1sonder/thumb_sonder_(3).jpg","title":"Sonder","alt":"Sonder by Syria Pace","_id":"sonder_(3).jpg","collection":"1sonder","decorativeCollectionName":"sonder","width":1920,"height":1259},{"uri":"/assets/pictures/1sonder/sonder_(2).jpg","thumb_uri":"/assets/thumbnails/1sonder/thumb_sonder_(2).jpg","title":"Sonder","alt":"Sonder by Syria Pace","_id":"sonder_(2).jpg","collection":"1sonder","decorativeCollectionName":"sonder","width":1920,"height":1258},{"uri":"/assets/pictures/1sonder/sonder_(9).jpg","thumb_uri":"/assets/thumbnails/1sonder/thumb_sonder_(9).jpg","title":"Sonder","alt":"Sonder by Syria Pace","_id":"sonder_(9).jpg","collection":"1sonder","decorativeCollectionName":"sonder","width":1919,"height":1282},{"uri":"/assets/pictures/4ex-bagnoli-futura/ex-bagnoli-futura_(7).jpg","thumb_uri":"/assets/thumbnails/4ex-bagnoli-futura/thumb_ex-bagnoli-futura_(7).jpg","title":"Ex Bagnoli Futura","alt":"Ex Bagnoli Futura by Syria Pace","_id":"ex-bagnoli-futura_(7).jpg","collection":"4ex-bagnoli-futura","decorativeCollectionName":"ex-bagnoli-futura","width":3091,"height":2048},{"uri":"/assets/pictures/4ex-bagnoli-futura/ex-bagnoli-futura_(2).jpg","thumb_uri":"/assets/thumbnails/4ex-bagnoli-futura/thumb_ex-bagnoli-futura_(2).jpg","title":"Ex Bagnoli Futura","alt":"Ex Bagnoli Futura by Syria Pace","_id":"ex-bagnoli-futura_(2).jpg","collection":"4ex-bagnoli-futura","decorativeCollectionName":"ex-bagnoli-futura","width":3091,"height":2048},{"uri":"/assets/pictures/4ex-bagnoli-futura/ex-bagnoli-futura_(5).jpg","thumb_uri":"/assets/thumbnails/4ex-bagnoli-futura/thumb_ex-bagnoli-futura_(5).jpg","title":"Ex Bagnoli Futura","alt":"Ex Bagnoli Futura by Syria Pace","_id":"ex-bagnoli-futura_(5).jpg","collection":"4ex-bagnoli-futura","decorativeCollectionName":"ex-bagnoli-futura","width":3091,"height":2048},{"uri":"/assets/pictures/4ex-bagnoli-futura/ex-bagnoli-futura_(4).jpg","thumb_uri":"/assets/thumbnails/4ex-bagnoli-futura/thumb_ex-bagnoli-futura_(4).jpg","title":"Ex Bagnoli Futura","alt":"Ex Bagnoli Futura by Syria Pace","_id":"ex-bagnoli-futura_(4).jpg","collection":"4ex-bagnoli-futura","decorativeCollectionName":"ex-bagnoli-futura","width":3091,"height":2048},{"uri":"/assets/pictures/4ex-bagnoli-futura/ex-bagnoli-futura_(6).jpg","thumb_uri":"/assets/thumbnails/4ex-bagnoli-futura/thumb_ex-bagnoli-futura_(6).jpg","title":"Ex Bagnoli Futura","alt":"Ex Bagnoli Futura by Syria Pace","_id":"ex-bagnoli-futura_(6).jpg","collection":"4ex-bagnoli-futura","decorativeCollectionName":"ex-bagnoli-futura","width":3091,"height":2048},{"uri":"/assets/pictures/4ex-bagnoli-futura/ex-bagnoli-futura_(3).jpg","thumb_uri":"/assets/thumbnails/4ex-bagnoli-futura/thumb_ex-bagnoli-futura_(3).jpg","title":"Ex Bagnoli Futura","alt":"Ex Bagnoli Futura by Syria Pace","_id":"ex-bagnoli-futura_(3).jpg","collection":"4ex-bagnoli-futura","decorativeCollectionName":"ex-bagnoli-futura","width":3091,"height":2048},{"uri":"/assets/pictures/4ex-bagnoli-futura/ex-bagnoli-futura_(1).jpg","thumb_uri":"/assets/thumbnails/4ex-bagnoli-futura/thumb_ex-bagnoli-futura_(1).jpg","title":"Ex Bagnoli Futura","alt":"Ex Bagnoli Futura by Syria Pace","_id":"ex-bagnoli-futura_(1).jpg","collection":"4ex-bagnoli-futura","decorativeCollectionName":"ex-bagnoli-futura","width":3091,"height":2048}]